odoo/addons/res_company_active/README.rst
odoo/addons/res_company_active/__init__.py
odoo/addons/res_company_active/__manifest__.py
odoo/addons/res_company_active/demo/res_company.xml
odoo/addons/res_company_active/demo/res_groups.xml
odoo/addons/res_company_active/i18n/fr.po
odoo/addons/res_company_active/i18n/hr.po
odoo/addons/res_company_active/i18n/res_company_active.pot
odoo/addons/res_company_active/models/__init__.py
odoo/addons/res_company_active/models/res_company.py
odoo/addons/res_company_active/readme/CONTRIBUTORS.rst
odoo/addons/res_company_active/readme/DESCRIPTION.rst
odoo/addons/res_company_active/static/description/icon.png
odoo/addons/res_company_active/static/description/index.html
odoo/addons/res_company_active/static/description/res_company_form.png
odoo/addons/res_company_active/static/description/validation_error.png
odoo/addons/res_company_active/tests/__init__.py
odoo/addons/res_company_active/tests/test_module.py
odoo/addons/res_company_active/views/view_res_company.xml
odoo12_addon_res_company_active-12.0.1.0.0.99.dev9.dist-info/METADATA
odoo12_addon_res_company_active-12.0.1.0.0.99.dev9.dist-info/WHEEL
odoo12_addon_res_company_active-12.0.1.0.0.99.dev9.dist-info/top_level.txt
odoo12_addon_res_company_active-12.0.1.0.0.99.dev9.dist-info/RECORD
